maria2csv/maria2csv.py
maria2csv-0.0.1.dist-info/LICENSE
maria2csv-0.0.1.dist-info/METADATA
maria2csv-0.0.1.dist-info/WHEEL
maria2csv-0.0.1.dist-info/entry_points.txt
maria2csv-0.0.1.dist-info/top_level.txt
maria2csv-0.0.1.dist-info/RECORD
